relkeyword/CorpusAnalyzer.py
relkeyword/Grants-20230219.csv
relkeyword/KeywordSuggester.py
relkeyword/__init__.py
relkeyword/test.py
relkeyword-0.0.2.dist-info/METADATA
relkeyword-0.0.2.dist-info/WHEEL
relkeyword-0.0.2.dist-info/licenses/LICENSE
relkeyword-0.0.2.dist-info/RECORD
