Metadata-Version: 2.1
Name: relkeyword
Version: 0.0.2
Summary: This package takes a user-submitted corpus, processes the corpus, and will be able to recommend keywords based on initial keyword suggestions.
Project-URL: Homepage, https://github.com/pypa/sampleproject
Project-URL: Bug Tracker, https://github.com/pypa/sampleproject/issues
Author-email: James Xie <jamestx2@illinois.edu>
License-File: LICENSE
Classifier: License :: OSI Approved :: MIT License
Classifier: Operating System :: OS Independent
Classifier: Programming Language :: Python :: 3
Requires-Python: >=3.7
